flamp_ru/__init__.py
flamp_ru/flamp_ru.py
flamp_ru-0.1.3.dist-info/LICENSE
flamp_ru-0.1.3.dist-info/METADATA
flamp_ru-0.1.3.dist-info/WHEEL
flamp_ru-0.1.3.dist-info/top_level.txt
flamp_ru-0.1.3.dist-info/RECORD
